weasel_make/__init__.py
weasel_make/weasel.py
weasel_make-0.3.2.dist-info/LICENSE
weasel_make-0.3.2.dist-info/METADATA
weasel_make-0.3.2.dist-info/WHEEL
weasel_make-0.3.2.dist-info/entry_points.txt
weasel_make-0.3.2.dist-info/top_level.txt
weasel_make-0.3.2.dist-info/RECORD
