Metadata-Version: 2.1
Name: weasel-make
Version: 0.3.2
Summary: A Makefile-compatibile Build Tool
Home-page: https://github.com/mirror12k/weasel-make
Author: Mirror12k
License: MIT
Keywords: make build-tool weasel makefile
Classifier: Programming Language :: Python :: 3
Classifier: License :: OSI Approved :: MIT License
License-File: LICENSE
